devops_microsoft_client_etl/__init__.py
devops_microsoft_client_etl/factory/__init__.py
devops_microsoft_client_etl/factory/factory.py
devops_microsoft_client_etl/factory/service_enum.py
devops_microsoft_client_etl/service/__init__.py
devops_microsoft_client_etl/service/tfs_service.py
devops_microsoft_client_etl-4.0.0.dist-info/METADATA
devops_microsoft_client_etl-4.0.0.dist-info/WHEEL
devops_microsoft_client_etl-4.0.0.dist-info/top_level.txt
devops_microsoft_client_etl-4.0.0.dist-info/RECORD
