Metadata-Version: 2.1
Name: devops-microsoft-client-etl
Version: 4.0.0
Summary: Responsible for sending commands to Seon DevOps microsoft job
Home-page: https://gitlab.com/integration_seon/libs/application/clockify
Author: Paulo Sergio dos Santo Junior
Author-email: paulossjuniort@gmail.com
License: UNKNOWN
Platform: UNKNOWN
Classifier: Programming Language :: Python :: 3
Classifier: License :: OSI Approved :: MIT License
Classifier: Operating System :: OS Independent
Requires-Dist: rabbitmqX
